pytest_passrunner/__init__.py
pytest_passrunner/__version__.py
pytest_passrunner/tests/__init__.py
pytest_passrunner/tests/test_plugin.py
pytest_passrunner-1.0.0.dist-info/LICENSE
pytest_passrunner-1.0.0.dist-info/METADATA
pytest_passrunner-1.0.0.dist-info/WHEEL
pytest_passrunner-1.0.0.dist-info/entry_points.txt
pytest_passrunner-1.0.0.dist-info/top_level.txt
pytest_passrunner-1.0.0.dist-info/RECORD
