Metadata-Version: 2.1
Name: pytest-passrunner
Version: 1.0.0
Summary: Pytest plugin providing the 'run_on_pass' marker
Home-page: UNKNOWN
Author: Ellert van der Velden
Author-email: ellert_vandervelden@outlook.com
License: BSD-3
Project-URL: Source Code, https://github.com/1313e/pytest-passrunner
Keywords: pytest passrunner plugin marker
Platform: Windows
Platform: Mac OS-X
Platform: Linux
Platform: Unix
Classifier: Development Status :: 5 - Production/Stable
Classifier: Intended Audience :: Developers
Classifier: License :: OSI Approved :: BSD License
Classifier: Natural Language :: English
Classifier: Operating System :: MacOS
Classifier: Operating System :: Microsoft :: Windows
Classifier: Operating System :: Unix
Classifier: Programming Language :: Python
Classifier: Programming Language :: Python :: 3
Classifier: Programming Language :: Python :: 3.6
Classifier: Programming Language :: Python :: 3.7
Classifier: Programming Language :: Python :: 3.8
Classifier: Programming Language :: Python :: 3.9
Classifier: Topic :: Utilities
Classifier: Framework :: Pytest
Requires-Python: >=3.6, <4
Requires-Dist: pytest (>=4.6.0)
